{"KxxEqYMNhKpuT/5zD0DCTw==":"acando-catalog-716x696.png","ljsTdrvzcGr8G2DQesC3lA==":"sbn-logo-original-700x675.png","VP0hn3Cxb0t1Te6YiqdiSA==":"sbn-logo-facebook-527x276.png","b0623PGR9y9t4/pFuFqWXQ==":"mbr-700x467.jpg","KkoMtlfaC6YUL/dxU98unQ==":"mbr-1-700x467.jpg","l8vla6ZYHQ1ErJIcvncvAg==":"mbr-2-700x467.jpg","bsrKjdztjEF4Bs3T5Yf1IQ==":"sdg-transparent-700x434.png","QOL0WAEtXmryI7fEq9PaZg==":"smart-cities-klub-fb-527x276.jpg","Xo1kkJIPA331h+eO8Coa8w==":"mbr-3-700x467.jpg","CXSA5iUN73QajBVRgpwkZw==":"arendalsuka-1080x810.jpg","99TzXa+nRDcDpnDPFVXrlQ==":"mbr-1920x1280.jpg","wEJ2WAWx1N1RajsvJDJXAQ==":"background1.jpg","cieaVf7bn7tVZaXbu4/4/g==":"mbr-972x648.jpg"}